[
    {
        "jalurIkon": "instagram.svg",
        "kepsyen":"Instagram Personal",
        "link": "https://www.instagram.com/azzam_29_12"
    },
    {
        "jalurIkon": "instagram.svg",
        "kepsyen":"Instagram Math Account",
        "link": "https://www.instagram.com/haxuv.world"
    },
    {
        "jalurIkon": "linkedin.svg",
        "kepsyen":"LinkedIn",
        "link": "https://www.linkedin.com/in/azzam-labib-hakim-b8212b1a3/"
    },    
    {
        "jalurIkon": "xtwitter.svg",
        "kepsyen":"Twitter / X",
        "link": "https://twitter.com/xeratha_haxuv/"
    },    
    {
        "jalurIkon": "github.svg",
        "kepsyen":"Github",
        "link": "https://github.com/azzam2912"
    }
]